area_calculator_dci.py
area_calculator_dci_march18-0.0.3.dist-info/LICENSE
area_calculator_dci_march18-0.0.3.dist-info/METADATA
area_calculator_dci_march18-0.0.3.dist-info/WHEEL
area_calculator_dci_march18-0.0.3.dist-info/top_level.txt
area_calculator_dci_march18-0.0.3.dist-info/RECORD
