Metadata-Version: 2.1
Name: area-calculator-dci-march18
Version: 0.0.3
Summary: Calculate areas of geometrical figures
Author: Victor M
Classifier: Programming Language :: Python :: 3
Classifier: License :: OSI Approved :: MIT License
Classifier: Operating System :: OS Independent
Requires-Python: >=3.6
License-File: LICENSE
